codemod2/__init__.py
codemod2/base.py
codemod2/helpers.py
codemod2/patch.py
codemod2/position.py
codemod2/query.py
codemod2/terminal_helper.py
codemod2-0.2.4.dist-info/LICENSE
codemod2-0.2.4.dist-info/METADATA
codemod2-0.2.4.dist-info/WHEEL
codemod2-0.2.4.dist-info/entry_points.txt
codemod2-0.2.4.dist-info/RECORD
