Metadata-Version: 2.1
Name: codemod2
Version: 0.2.4
Summary: a fork of facebook/codemod using pcre compatible regular expressions
License: Apache-2.0
Author: Martin Drohmann
Author-email: mdrohmann@gmail.com
Requires-Python: >=3.11,<4.0
Classifier: License :: OSI Approved :: Apache Software License
Classifier: Programming Language :: Python :: 3
Classifier: Programming Language :: Python :: 3.11
Classifier: Programming Language :: Python :: 3.12
Requires-Dist: regex (>=2023.12.25,<2024.0.0)
